Metadata-Version: 2.1
Name: immuno-compass
Version: 2.2
Summary: COMPASS: Generalizable AI predicts immunotherapy outcomes across cancers and treatments.
Home-page: https://github.com/mims-harvard/COMPASS/tree/main
Author: WanXiang Shen
License-File: LICENSE
Requires-Dist: torch==1.13.1
Requires-Dist: torchvision==0.14.1
Requires-Dist: torchaudio==0.13.1
Requires-Dist: einops
Requires-Dist: scikit-learn
Requires-Dist: umap-learn
Requires-Dist: wandb
Requires-Dist: matplotlib
Requires-Dist: seaborn
Requires-Dist: statannotations==0.6.0
Requires-Dist: comut
Requires-Dist: gseapy
Requires-Dist: tidepy
Requires-Dist: colorcet
Requires-Dist: gdown
Requires-Dist: qnorm
Requires-Dist: openpyxl
Requires-Dist: plotly
Provides-Extra: dev
Requires-Dist: pytest; extra == "dev"
